{
  "portfolios": [
    {
      "title": "Portfolio DoneJob",
      "body": "loremm..",
      "category": "Frontend",
      "id": 1
    },
    {
      "title": "Portfolio Social Media",
      "body": "loremm..",
      "category": "Social Media Specialist",
      "id": 2
    },
    {
      "title": "Portfolio Design",
      "body": "loremm..",
      "category": "Design",
      "id": 3
    },
    {
      "title": "Portfolio BodyCupping",
      "body": "loremm..",
      "category": "Frontend",
      "id": 4
    }
  ]
}
